omnigenai_toolkit/__init__.py
omnigenai_toolkit/chatbot.py
omnigenai_toolkit-1.0.1.dist-info/LICENSE
omnigenai_toolkit-1.0.1.dist-info/METADATA
omnigenai_toolkit-1.0.1.dist-info/WHEEL
omnigenai_toolkit-1.0.1.dist-info/top_level.txt
omnigenai_toolkit-1.0.1.dist-info/RECORD
