Metadata-Version: 2.2
Name: omnigenai_toolkit
Version: 1.0.1
Summary: A Python package for Generative AI applications
Home-page: https://github.com/gopalakrishnanarjun/omnigenai_toolkit.git
Author: Gopalakrishnan Arjunan
Author-email: gopalakrishnana02@gmail.com
Classifier: Programming Language :: Python :: 3
Classifier: License :: OSI Approved :: MIT License
Classifier: Operating System :: OS Independent
Requires-Python: >=3.7
License-File: LICENSE
Dynamic: author
Dynamic: author-email
Dynamic: classifier
Dynamic: description
Dynamic: description-content-type
Dynamic: home-page
Dynamic: requires-python
Dynamic: summary
